starlette_exporter/__init__.py
starlette_exporter/labels.py
starlette_exporter/middleware.py
starlette_exporter/optional_metrics.py
starlette_exporter/py.typed
starlette_exporter-0.23.0.dist-info/LICENSE
starlette_exporter-0.23.0.dist-info/METADATA
starlette_exporter-0.23.0.dist-info/WHEEL
starlette_exporter-0.23.0.dist-info/top_level.txt
starlette_exporter-0.23.0.dist-info/RECORD
