Metadata-Version: 2.1
Name: starlette_exporter
Version: 0.23.0
Summary: Prometheus metrics exporter for Starlette applications.
Home-page: https://github.com/stephenhillier/starlette_exporter
Author: Stephen Hillier
Author-email: stephenhillier@gmail.com
License: Apache License 2.0
Requires-Python: >=3.8
License-File: LICENSE
Requires-Dist: prometheus_client>=0.12
Requires-Dist: starlette>=0.35
